windcomponents.py
windcomponents-0.6.dist-info/LICENSE.txt
windcomponents-0.6.dist-info/METADATA
windcomponents-0.6.dist-info/WHEEL
windcomponents-0.6.dist-info/top_level.txt
windcomponents-0.6.dist-info/RECORD
