Metadata-Version: 2.1
Name: windcomponents
Version: 0.6
Summary: Python library for calculating aircraft cross- and tailwind components on a runway
Author: Sebastiaan Menger
Author-email: s.menger001@gmail.com
License: GPL-3.0
Classifier: License :: OSI Approved :: GNU General Public License v3 (GPLv3)
Classifier: Programming Language :: Python :: 3
Classifier: Operating System :: OS Independent
Requires-Python: >=3.6
License-File: LICENSE.txt
